iaewoojinmysql/__init__.py
iaewoojinmysql/iaewoojinmysql.py
iaewoojinpymysql/__init__.py
iaewoojinpymysql/iaewoojinpymysql.py
woojintest-0.1.dist-info/METADATA
woojintest-0.1.dist-info/WHEEL
woojintest-0.1.dist-info/top_level.txt
woojintest-0.1.dist-info/RECORD
