Metadata-Version: 2.1
Name: woojintest
Version: 0.1
Summary: pymysql Simple used
Home-page: https://github.com/IAEWoojinCho
Author: Woojin Cho
Author-email: wooju_1@iae.re.kr
License: UNKNOWN
Platform: UNKNOWN
Classifier: Programming Language :: Python :: 3
Classifier: License :: OSI Approved :: MIT License
Classifier: Operating System :: OS Independent
Requires-Python: >=3.6
